LICENSE
README.md
kafka_consumer/__init__.py
kafka_consumer/admin.py
kafka_consumer/connection_cleaning.py
kafka_consumer/consumer.py
kafka_consumer/exceptions.py
kafka_consumer/fields.py
kafka_consumer/locale/en/LC_MESSAGES/django.po
kafka_consumer/locale/pl/LC_MESSAGES/django.po
kafka_consumer/management/__init__.py
kafka_consumer/management/commands/__init__.py
kafka_consumer/management/commands/consume.py
kafka_consumer/management/commands/consume_junk_messages.py
kafka_consumer/managers.py
kafka_consumer/messages/__init__.py
kafka_consumer/messages/base.py
kafka_consumer/messages/dispatcher.py
kafka_consumer/messages/processors.py
kafka_consumer/migrations/0001_initial.py
kafka_consumer/migrations/__init__.py
kafka_consumer/models.py
kafka_consumer/settings.py
kafka_consumer/subscribers/__init__.py
kafka_consumer/subscribers/base.py
kafka_consumer/tests/__init__.py
kafka_consumer/tests/helpers.py
kafka_consumer/tests/test_base_subscriber.py
kafka_consumer/tests/test_batch_processor.py
kafka_consumer/tests/test_consume_command.py
kafka_consumer/tests/test_junk_message.py
kafka_consumer/tests/test_message_dispatcher.py
kafka_consumer/utils.py
django_kafka_consumer-2.0.0.dist-info/LICENSE
django_kafka_consumer-2.0.0.dist-info/WHEEL
django_kafka_consumer-2.0.0.dist-info/METADATA
django_kafka_consumer-2.0.0.dist-info/RECORD
