Metadata-Version: 2.1
Name: django-kafka-consumer
Version: 2.0.0
Summary: 
Home-page: https://github.com/innovationinit/django-kafka-consumer
License: BSD-2-Clause
Author: IIIT
Author-email: github@iiit.pl
Requires-Python: >=3.7,<3.10
Classifier: License :: OSI Approved :: BSD License
Classifier: Programming Language :: Python :: 3
Classifier: Programming Language :: Python :: 3.7
Classifier: Programming Language :: Python :: 3.8
Classifier: Programming Language :: Python :: 3.9
Requires-Dist: Django (>=2.0,<3.0)
Requires-Dist: kafka-python (==2.0.2)
Requires-Dist: pytz (>=2021.3,<2022.0)
Project-URL: Repository, https://github.com/innovationinit/django-kafka-consumer
